Capstone.v
//accumulator right shift register
module accumulator_shift_reg (input CLK, //Clock
							  input Si, //Serial in
							  input L, //Load enable
							  input [7:0] Load, //Load value
							  input PoutE, //Parralell out enable
							  output Sout, //Shift out
							  output reg [7:0] Pout //Parralell out
							  ); 
	reg Sout;
	reg [7:0] accumulator;

	always @ (CLK) begin
		if (L) begin 
			accumulator = Load;
		end
		
	end

	always @ (posedge CLK) begin
		if (!L)
			Sout = accumulator[0];
		if (PoutE)
			Pout = accumulator;
	end

	always @ (negedge CLK) begin
		if (!L)
			accumulator = {Si, accumulator[7:1]};

		if (PoutE)
			Pout = accumulator;
	end
endmodule

// cyclical shift register
module subtrahend_shift_reg (input CLK, //Clock
						 input L, //Load enable
						 input [7:0] Load, //Load 
						 output Sout //Serial out
						 );

	reg Sout;
	reg [7:0] subtrahend;

	always @ (CLK) begin
		if (L) 
			subtrahend = Load;
	end	

	always @ (posedge CLK) begin
		if (!L)
			Sout = subtrahend[0];
	end	
	always @ (negedge CLK) begin
		if (!L) 
			subtrahend = {subtrahend[0], subtrahend[7:1]};
	end
endmodule


//Module for borrow flipflop
module borrow_flipflop (input D, //Input
                       input CLK, 
					   input R, //Reset
                       output reg Q //Output
					   ); 
    always @(negedge CLK) begin //executes block at every neg edge of clock // print current values to output console
        if (!R)
			Q = D;
		else
			Q = 0;
    end
endmodule

//Module for full subtractor
module full_subtractor (input X, //Minuend
                       input Y, //Subtrahend
                       input Bin, //Borrow in
                       output D, //Difference
                       output Bout //Borrow out
					   ); 
    
    assign D = X ^ Y ^ Bin; // D(x, y, Bin) = x ⊕ y ⊕ Bin
    assign Bout = (~X & Bin) | (Y & Bin) | (~X & Y); //Bout(x, y, Bin) = x'*Bin + Y*Bin + x'y
endmodule

// Status Register module
module status_register(input [7:0] X,   // Minuend
					   input [7:0] Y,   // Subtrahend
					   input clk, // Clock
					   output reg SReg1, // Status Register Z, 0x00
					   output reg SReg2, // Status Register N, negative
					   output reg SReg3  // Status Register V, overflow
					   );
	always @ (negedge clk) begin
		if (X == Y)
			SReg1 = 1;
			else
			SReg1 = 0;
		if (X < Y)
			SReg2 = 1;
		else
			SReg2 = 0;
		if ((Y - X) >= 128)
			SReg3 = 1;
		else
			SReg3 = 0;
	end
endmodule	


	

module top (input St, //start signal
			input [7:0] eightBitMinuend,
			input [7:0] eightBitSubtrahend,
			output [7:0] eightBitDifference,
			output StatusRegZ,
			output StatusRegN,
			output StatusRegV
			);
	reg [7:0] acc;
	reg CLK = 0;
	reg LAccumulator = 1;
	wire minuend;
	reg PoutE = 0;
	wire [7:0] Difference;
	wire Z, N, V; 

	accumulator_shift_reg accumulatorReg(
		.CLK(CLK), .Si(Si), .L(LAccumulator), .Load(eightBitMinuend), .Sout(minuend), .PoutE(PoutE), .Pout(eightBitDifference)
	);

	reg LSubtrahend = 1;
	wire subtrahend;

	subtrahend_shift_reg subtrahendReg(
		.CLK(CLK), .L(LSubtrahend), .Load(eightBitSubtrahend), .Sout(subtrahend)
	);

	wire Bout;
	wire Bin;
	reg R = 1;

	borrow_flipflop flipflop(
		.D(Bout), .CLK(CLK), .R(R), .Q(Bin)
	);

	full_subtractor subtractor(
		.X(minuend), .Y(subtrahend), .Bin(Bin), .D(Si), .Bout(Bout)
	);

	status_register register(
		.X(eightBitMinuend), .Y(eightBitSubtrahend), .clk(CLK), .SReg1(StatusRegZ), .SReg2(StatusRegN), .SReg3(StatusRegV)
	);

	initial begin
		$dumpfile("sss.vcd");
		$dumpvars(0, top);
	end
	
	always begin
		#10 
		R = 0;
		CLK = 0;
		LAccumulator = 0;
		LSubtrahend = 0;
		#10
		CLK = ~CLK;
	end


	always #180 begin
		PoutE = 1;
		#10
		$finish;
	end
endmodule

/////////////////////////////
////top module Testbench////
///////////////////////////


module topTB; //Testbench for control circuit
    reg St; //Input registers

	reg [7:0] eightBitMinuend = 8'b00110100;
	reg [7:0] eightBitSubtrahend = 8'b11110111;
	wire [7:0] eightBitDifference;
	wire Z, N, V;

	top UUT(.St(St), .eightBitMinuend(eightBitMinuend), .eightBitSubtrahend(eightBitSubtrahend), .eightBitDifference(eightBitDifference), .StatusRegZ(Z), .StatusRegN(N), .StatusRegV(V)); // Unit Under Test
	// Test Execution
	initial begin
		#190
		$display(" %b {%d}", eightBitMinuend, eightBitMinuend);
		$display("-%b {%d}", eightBitSubtrahend, eightBitSubtrahend);
		$display("------------");
		$display(" %b {%d}\n", eightBitDifference, eightBitDifference);
		$display("Status Registers:");
		$display("Z= %b  N= %b  V= %b", Z, N, V);
	end
endmodule

build/sss.vcd
$date
	Thu Aug 04 17:58:24 2022
$end
$version
	Icarus Verilog
$end
$timescale
	1s
$end
$scope module topTB $end
$scope module UUT $end
$var wire 1 ! St $end
$var wire 8 " eightBitMinuend [7:0] $end
$var wire 8 # eightBitSubtrahend [7:0] $end
$var wire 1 $ subtrahend $end
$var wire 1 % minuend $end
$var wire 8 & eightBitDifference [7:0] $end
$var wire 1 ' StatusRegZ $end
$var wire 1 ( StatusRegV $end
$var wire 1 ) StatusRegN $end
$var wire 1 * Si $end
$var wire 1 + Bout $end
$var wire 1 , Bin $end
$var reg 1 - CLK $end
$var reg 1 . LAccumulator $end
$var reg 1 / LSubtrahend $end
$var reg 1 0 PoutE $end
$var reg 1 1 R $end
$scope module accumulatorReg $end
$var wire 1 - CLK $end
$var wire 1 . L $end
$var wire 8 2 Load [7:0] $end
$var wire 1 0 PoutE $end
$var wire 1 * Si $end
$var reg 8 3 Pout [7:0] $end
$var reg 1 % Sout $end
$var reg 8 4 accumulator [7:0] $end
$upscope $end
$scope module flipflop $end
$var wire 1 - CLK $end
$var wire 1 1 R $end
$var wire 1 + D $end
$var reg 1 , Q $end
$upscope $end
$scope module register $end
$var wire 8 5 X [7:0] $end
$var wire 8 6 Y [7:0] $end
$var wire 1 - clk $end
$var reg 1 ' SReg1 $end
$var reg 1 ) SReg2 $end
$var reg 1 ( SReg3 $end
$upscope $end
$scope module subtractor $end
$var wire 1 , Bin $end
$var wire 1 + Bout $end
$var wire 1 * D $end
$var wire 1 % X $end
$var wire 1 $ Y $end
$upscope $end
$scope module subtrahendReg $end
$var wire 1 - CLK $end
$var wire 1 / L $end
$var wire 8 7 Load [7:0] $end
$var reg 1 $ Sout $end
$var reg 8 8 subtrahend [7:0] $end
$upscope $end
$upscope $end
$upscope $end
$enddefinitions $end
$comment Show the parameter values. $end
$dumpall
$end
#0
$dumpvars
b11110111 8
b11110111 7
b11110111 6
b110100 5
b110100 4
bx 3
b110100 2
11
00
1/
1.
0-
0,
x+
x*
1)
1(
0'
bx &
x%
x$
b11110111 #
b110100 "
x!
$end
#10
0/
0.
01
#20
1+
1*
0%
1$
1-
#30
0*
1,
b11111011 8
b10011010 4
0-
#40
1-
#50
b1001101 4
b11111101 8
0-
#60
1*
1%
1-
#70
b11111110 8
b10100110 4
0-
#80
0$
0%
1-
#90
b11010011 4
b1111111 8
0-
#100
1%
1$
1-
#110
b10111111 8
b11101001 4
0-
#120
1-
#130
b11110100 4
b11011111 8
0-
#140
0*
0%
1-
#150
b11101111 8
b1111010 4
0-
#160
1-
#170
b111101 4
b11110111 8
0-
#180
1*
b111101 &
b111101 3
1%
1-
10
#190
b11111011 8
b10011110 &
b10011110 3
b10011110 4
0-
