Capstone.v
//accumulator right shift register
module accumulator_shift_reg (input CLK, //Clock
							  input Si, //Serial in
							  input L, //Load enable
							  input [7:0] Load, //Load value
							  input PoutE, //Parralell out enable
							  output Sout, //Shift out
							  output reg [7:0] Pout //Parralell out
							  ); 
	reg Sout;
	reg [7:0] accumulator;

	always @ (CLK) begin
		if (L) begin 
			accumulator = Load;
		end
		
	end

	always @ (posedge CLK) begin
		if (!L)
			Sout = accumulator[0];
		if (PoutE)
			Pout = accumulator;
	end

	always @ (negedge CLK) begin
		if (!L)
			accumulator = {Si, accumulator[7:1]};

		if (PoutE)
			Pout = accumulator;
	end
endmodule

// cyclical shift register
module addend_shift_reg (input CLK, //Clock
						 input L, //Load enable
						 input [7:0] Load, //Load 
						 output Sout //Serial out
						 );

	reg Sout;
	reg [7:0] subtrahend;

	always @ (CLK) begin
		if (L) begin
			subtrahend = Load;
		end
	end	
	
	always @ (posedge CLK) begin
		if (!L)
			Sout = subtrahend[0];
	end	
	always @ (negedge CLK) begin
		if (!L) 
			subtrahend = {subtrahend[0], subtrahend[7:1]};
	end
endmodule


//Module for borrow flipflop
module borrow_flipflop (input D, //Input
                       input CLK, 
					   input R, //Reset
                       output reg Q //Output
					   ); 
    always @(negedge CLK) begin //executes block at every neg edge of clock // print current values to output console
        if (!R)
			Q = D;
		else
			Q = 0;
    end
endmodule

//Module for full subtractor
module full_subtractor (input X, //Minuend
                       input Y, //Subtrahend
                       input Bin, //Borrow in
                       output D, //Difference
                       output Bout //Borrow out
					   ); 
    
    assign D = X ^ Y ^ Bin; // D(x, y, Bin) = x ⊕ y ⊕ Bin
    assign Bout = (~X & Bin) | (Y & Bin) | (~X & Y); //Bout(x, y, Bin) = x'*Bin + Y*Bin + x'y
endmodule

module top (input St, //start signal
			input [7:0] eightBitMinuend,
			input [7:0] eightBitSubtrahend,
			output [7:0] eightBitDifference
			);
	reg [7:0] acc;
	reg CLK = 0;
	reg LAccumulator = 1;
	wire minuend;
	reg PoutE = 0;
	wire [7:0] Difference;

	accumulator_shift_reg accumulatorReg(
		.CLK(CLK), .Si(Si), .L(LAccumulator), .Load(eightBitMinuend), .Sout(minuend), .PoutE(PoutE), .Pout(eightBitDifference)
	);

	reg LSubtrahend = 1;
	wire subtrahend;

	addend_shift_reg subtrahendReg(
		.CLK(CLK), .L(LSubtrahend), .Load(eightBitSubtrahend), .Sout(subtrahend)
	);

	wire Bout;
	wire Bin;
	reg R = 1;

	borrow_flipflop flipflop(
		.D(Bout), .CLK(CLK), .R(R), .Q(Bin)
	);

	full_subtractor subtractor(
		.X(minuend), .Y(subtrahend), .Bin(Bin), .D(Si), .Bout(Bout)
	);

	initial begin
		$dumpfile("sss.vcd");
		$dumpvars(0, top);
	end
	
	always begin
		#10 
		R = 0;
		CLK = 0;
		LAccumulator = 0;
		LSubtrahend = 0;
		//$display("\nCLK: %b Min: %b, Sub: %b, D: %b Bout: %b",CLK,  minuend, subtrahend, Si, Bout);
		#10
		CLK = ~CLK;
	end


	always #180 begin
		PoutE = 1;
		#10
		//$display("Accu: ", Difference);
		$finish;

	end
endmodule

/////////////////////////////
////top module Testbench////
///////////////////////////


module topTB; //Testbench for control circuit
    reg St; //Input registers

	reg [7:0] eightBitMinuend = 8'b10100101 ;
	reg [7:0] eightBitSubtrahend = 8'b10000011;
	wire [7:0] eightBitDifference;

	top UUT(.St(St), .eightBitMinuend(eightBitMinuend), .eightBitSubtrahend(eightBitSubtrahend), .eightBitDifference(eightBitDifference)); // Unit Under Test
	// Test Execution
	initial begin
		#190
		$display(" %b {%d}", eightBitMinuend, eightBitMinuend);
		$display("-%b {%d}", eightBitSubtrahend, eightBitSubtrahend);
		$display("------------");
		$display(" %b {%d}\n\n", eightBitDifference, eightBitDifference);
		// #190
		// 
		// $display(" %b {%d}", eightBitMinuend, eightBitMinuend);
		// $display("-%b {%d}", eightBitSubtrahend, eightBitSubtrahend);
		// $display("------------");
		// $display(" %b {%d}\n\n", eightBitDifference, );
	end
endmodule

build/sss.vcd
$date
	Thu Aug 04 14:29:12 2022
$end
$version
	Icarus Verilog
$end
$timescale
	1s
$end
$scope module topTB $end
$scope module UUT $end
$var wire 1 ! St $end
$var wire 8 " eightBitMinuend [7:0] $end
$var wire 8 # eightBitSubtrahend [7:0] $end
$var wire 1 $ subtrahend $end
$var wire 1 % minuend $end
$var wire 8 & eightBitDifference [7:0] $end
$var wire 1 ' Si $end
$var wire 1 ( Bout $end
$var wire 1 ) Bin $end
$var reg 1 * CLK $end
$var reg 1 + LAccumulator $end
$var reg 1 , LSubtrahend $end
$var reg 1 - PoutE $end
$var reg 1 . R $end
$scope module accumulatorReg $end
$var wire 1 * CLK $end
$var wire 1 + L $end
$var wire 8 / Load [7:0] $end
$var wire 1 - PoutE $end
$var wire 1 ' Si $end
$var reg 8 0 Pout [7:0] $end
$var reg 1 % Sout $end
$var reg 8 1 accumulator [7:0] $end
$upscope $end
$scope module flipflop $end
$var wire 1 * CLK $end
$var wire 1 . R $end
$var wire 1 ( D $end
$var reg 1 ) Q $end
$upscope $end
$scope module subtractor $end
$var wire 1 ) Bin $end
$var wire 1 ( Bout $end
$var wire 1 ' D $end
$var wire 1 % X $end
$var wire 1 $ Y $end
$upscope $end
$scope module subtrahendReg $end
$var wire 1 * CLK $end
$var wire 1 , L $end
$var wire 8 2 Load [7:0] $end
$var reg 1 $ Sout $end
$var reg 8 3 subtrahend [7:0] $end
$upscope $end
$upscope $end
$upscope $end
$enddefinitions $end
$comment Show the parameter values. $end
$dumpall
$end
#0
$dumpvars
b10000011 3
b10000011 2
b10100101 1
bx 0
b10100101 /
1.
0-
1,
1+
0*
0)
x(
x'
bx &
x%
x$
b10000011 #
b10100101 "
x!
$end
#10
0,
0+
0.
#20
0(
0'
1%
1$
1*
#30
b11000001 3
b1010010 1
0*
#40
1(
1'
0%
1*
#50
0'
b10101001 1
b11100000 3
1)
0*
#60
0(
1%
0$
1*
#70
1'
0)
b1110000 3
b1010100 1
0*
#80
0'
0%
1*
#90
b101010 1
b111000 3
0*
#100
1*
#110
b11100 3
b10101 1
0*
#120
1'
1%
1*
#130
b10001010 1
b1110 3
0*
#140
0'
0%
1*
#150
b111 3
b1000101 1
0*
#160
1$
1%
1*
#170
b100010 1
b10000011 3
0*
#180
1(
1'
b100010 &
b100010 0
0%
1*
1-
#190
0'
1)
b11000001 3
b10010001 &
b10010001 0
b10010001 1
0*
